indexter/__init__.py
indexter/cli/__init__.py
indexter/cli/cli.py
indexter/cli/config.py
indexter/cli/store.py
indexter/config.py
indexter/exceptions.py
indexter/mcp/__init__.py
indexter/mcp/prompts.py
indexter/mcp/server.py
indexter/mcp/tools.py
indexter/models.py
indexter/parser/__init__.py
indexter/parser/models.py
indexter/parser/parser.py
indexter/parser/parsers/__init__.py
indexter/parser/parsers/base.py
indexter/parser/parsers/chunk.py
indexter/parser/parsers/css.py
indexter/parser/parsers/html.py
indexter/parser/parsers/javascript.py
indexter/parser/parsers/json.py
indexter/parser/parsers/markdown.py
indexter/parser/parsers/python.py
indexter/parser/parsers/rust.py
indexter/parser/parsers/toml.py
indexter/parser/parsers/typescript.py
indexter/parser/parsers/yaml.py
indexter/store/__init__.py
indexter/store/models.py
indexter/store/store.py
indexter/walker/__init__.py
indexter/walker/models.py
indexter/walker/walker.py
indexter-0.1.2.dist-info/WHEEL
indexter-0.1.2.dist-info/entry_points.txt
indexter-0.1.2.dist-info/METADATA
indexter-0.1.2.dist-info/RECORD
