Metadata-Version: 2.4
Name: indexter
Version: 0.1.2
Summary: CLI tool and MCP server for enhanced codebase context via RAG
Keywords: cli,mcp,rag,vector-search,tree-sitter,code-indexing,ai-agents
Author: Joe Badger
License-Expression: MIT
Classifier: Development Status :: 3 - Alpha
Classifier: Environment :: Console
Classifier: Intended Audience :: Developers
Classifier: License :: OSI Approved :: MIT License
Classifier: Operating System :: OS Independent
Classifier: Programming Language :: Python :: 3
Classifier: Programming Language :: Python :: 3.11
Classifier: Programming Language :: Python :: 3.12
Classifier: Programming Language :: Python :: 3.13
Classifier: Topic :: Software Development :: Libraries :: Python Modules
Classifier: Typing :: Typed
Requires-Dist: anyio>=4.0.0
Requires-Dist: pathspec>=0.12.1
Requires-Dist: qdrant-client[fastembed]>=1.12.0
Requires-Dist: pydantic>=2.10.0
Requires-Dist: pydantic-settings>=2.6.0
Requires-Dist: tomli>=2.0.0
Requires-Dist: tomlkit>=0.13.0
Requires-Dist: tree-sitter>=0.25.2
Requires-Dist: tree-sitter-language-pack>=0.13.0
Requires-Dist: docker>=7.0.0 ; extra == 'cli'
Requires-Dist: rich>=13.9.0 ; extra == 'cli'
Requires-Dist: typer>=0.12.0 ; extra == 'cli'
Requires-Dist: docker>=7.0.0 ; extra == 'full'
Requires-Dist: fastmcp>=0.4.1 ; extra == 'full'
Requires-Dist: rich>=13.9.0 ; extra == 'full'
Requires-Dist: typer>=0.12.0 ; extra == 'full'
Requires-Dist: fastmcp>=0.4.1 ; extra == 'mcp'
Requires-Python: >=3.11, <3.14
Project-URL: Homepage, https://github.com/jdbadger/indexter
Project-URL: Repository, https://github.com/jdbadger/indexter
Project-URL: Documentation, https://github.com/jdbadger/indexter#readme
Project-URL: Bug Tracker, https://github.com/jdbadger/indexter/issues
Project-URL: Changelog, https://github.com/jdbadger/indexter/blob/main/CHANGELOG.md
Provides-Extra: cli
Provides-Extra: core
Provides-Extra: full
Provides-Extra: mcp
